printt/__init__.py
printt/main.py
printt-0.1.2.dist-info/METADATA
printt-0.1.2.dist-info/WHEEL
printt-0.1.2.dist-info/RECORD
