Metadata-Version: 2.1
Name: printt
Version: 0.1.2
Summary: 
Author: tikendraw
Author-email: tikendraksahu1029@gmail.com
Requires-Python: >=3.11,<4.0
Classifier: Programming Language :: Python :: 3
Classifier: Programming Language :: Python :: 3.11
Classifier: Programming Language :: Python :: 3.12
Requires-Dist: rich (>=13.7.1,<14.0.0)
